optiwindnet/__init__.py
optiwindnet/api.py
optiwindnet/api_utils.py
optiwindnet/augmentation.py
optiwindnet/clustering.py
optiwindnet/crossings.py
optiwindnet/geometric.py
optiwindnet/importer.py
optiwindnet/interarraylib.py
optiwindnet/interface.py
optiwindnet/mesh.py
optiwindnet/pathfinding.py
optiwindnet/plotting.py
optiwindnet/repair.py
optiwindnet/svg.py
optiwindnet/synthetic.py
optiwindnet/themes.py
optiwindnet/utils.py
optiwindnet/version.py
optiwindnet/weighting.py
optiwindnet/MILP/__init__.py
optiwindnet/MILP/_core.py
optiwindnet/MILP/cplex.py
optiwindnet/MILP/fscip.py
optiwindnet/MILP/gurobi.py
optiwindnet/MILP/ortools.py
optiwindnet/MILP/pyomo.py
optiwindnet/MILP/scip.py
optiwindnet/baselines/__init__.py
optiwindnet/baselines/_core_hgs.py
optiwindnet/baselines/hgs.py
optiwindnet/baselines/lkh.py
optiwindnet/baselines/utils.py
optiwindnet/data/Albatros.osm.pbf
optiwindnet/data/Amrumbank West.osm.pbf
optiwindnet/data/Anholt.yaml
optiwindnet/data/Arkona.osm.pbf
optiwindnet/data/BARD Offshore 1.osm.pbf
optiwindnet/data/Baltic 2.osm.pbf
optiwindnet/data/Baltic Eagle.osm.pbf
optiwindnet/data/Beatrice.osm.pbf
optiwindnet/data/Belwind.osm.pbf
optiwindnet/data/Borkum Riffgrund 1.yaml
optiwindnet/data/Borkum Riffgrund 2.yaml
optiwindnet/data/Borkum Riffgrund 3.osm.pbf
optiwindnet/data/Borssele.yaml
optiwindnet/data/Butendiek.yaml
optiwindnet/data/CECEP Yangjiang Nanpeng Island.osm.pbf
optiwindnet/data/CGN Rudong Demonstration.osm.pbf
optiwindnet/data/Cazzaro-2022.yaml
optiwindnet/data/Cazzaro-2022G-140.yaml
optiwindnet/data/Cazzaro-2022G-210.yaml
optiwindnet/data/Coastal Virginia.osm.pbf
optiwindnet/data/DanTysk.yaml
optiwindnet/data/Deutsche Bucht.osm.pbf
optiwindnet/data/Dogger Bank A.yaml
optiwindnet/data/Dogger Bank B.osm.pbf
optiwindnet/data/Dogger Bank C.osm.pbf
optiwindnet/data/Dudgeon.yaml
optiwindnet/data/East Anglia ONE.yaml
optiwindnet/data/Fecamp.osm.pbf
optiwindnet/data/Galloper Inner.osm.pbf
optiwindnet/data/Gemini 1.osm.pbf
optiwindnet-0.1.6.dist-info/licenses/LICENSE.txt
optiwindnet-0.1.6.dist-info/METADATA
optiwindnet-0.1.6.dist-info/WHEEL
optiwindnet-0.1.6.dist-info/top_level.txt
optiwindnet-0.1.6.dist-info/RECORD
