Metadata-Version: 2.4
Name: optiwindnet
Version: 0.1.6
Summary: Tool for designing and optimizing the electrical cable network of offshore wind farms
Author-email: DTU Wind Energy <mikf@dtu.dk>, Mauricio Souza de Alencar <ma___@dtu.dk>, Amir Arasteh <am___@dtu.dk>
License-Expression: MIT
Project-URL: Homepage, https://gitlab.windenergy.dtu.dk/TOPFARM/OptiWindNet
Project-URL: Documentation, https://optiwindnet.readthedocs.io/
Project-URL: Download, https://optiwindnet.readthedocs.io/stable/setup.html#installation
Project-URL: Issue Tracker, https://github.com/DTUWindEnergy/OptiWindNet/issues
Project-URL: Release Notes, https://github.com/DTUWindEnergy/OptiWindNet/tags
Project-URL: Source, https://github.com/DTUWindEnergy/OptiWindNet
Keywords: optimization,wind farm,network,routing
Classifier: Development Status :: 4 - Beta
Classifier: Intended Audience :: Developers
Classifier: Intended Audience :: Science/Research
Classifier: Programming Language :: Python :: 3
Classifier: Operating System :: OS Independent
Classifier: Topic :: Software Development :: Libraries :: Python Modules
Classifier: Topic :: Scientific/Engineering
Requires-Python: >=3.11
License-File: LICENSE.txt
Requires-Dist: bidict>=0.23.1
Requires-Dist: bitarray>=3.4.2
Requires-Dist: condeltri>=0.0.3
Requires-Dist: darkdetect>=0.8.0
Requires-Dist: esy.osm.pbf>=0.1.1
Requires-Dist: hybgensea>=0.0.1
Requires-Dist: makefun>=1.15.6
Requires-Dist: matplotlib>=3.10.1
Requires-Dist: networkx>=3.6
Requires-Dist: numba>=0.62.1
Requires-Dist: numpy>=2.0
Requires-Dist: ortools>=9.12.4544
Requires-Dist: pony>=0.7.18
Requires-Dist: py>=1.11.0
Requires-Dist: Pyomo>=6.9.5
Requires-Dist: PyYAML>=6.0.2
Requires-Dist: scipy>=1.15.2
Requires-Dist: shapely>=2.0.7
Requires-Dist: svg.py>=1.6.0
Requires-Dist: utm>=0.7
Provides-Extra: solvers
Requires-Dist: cplex; extra == "solvers"
Requires-Dist: gurobipy; extra == "solvers"
Requires-Dist: highspy; extra == "solvers"
Requires-Dist: pyscipopt; extra == "solvers"
Provides-Extra: test
Requires-Dist: dill; extra == "test"
Requires-Dist: coverage; extra == "test"
Requires-Dist: pytest; extra == "test"
Requires-Dist: pytest-cov; extra == "test"
Requires-Dist: pytest-xdist; extra == "test"
Requires-Dist: psutil; extra == "test"
Requires-Dist: memory_profiler; extra == "test"
Requires-Dist: line_profiler; extra == "test"
Requires-Dist: optiwindnet[solvers]; extra == "test"
Provides-Extra: docs
Requires-Dist: sphinx; extra == "docs"
Requires-Dist: nbsphinx; extra == "docs"
Requires-Dist: myst-parser; extra == "docs"
Requires-Dist: myst-nb; extra == "docs"
Requires-Dist: furo; extra == "docs"
Requires-Dist: sphinx-versioned-docs; extra == "docs"
Requires-Dist: sphinx-autoapi; extra == "docs"
Requires-Dist: sphinx_copybutton; extra == "docs"
Requires-Dist: sphinx_sitemap; extra == "docs"
Requires-Dist: pypandoc; extra == "docs"
Requires-Dist: setuptools-scm; extra == "docs"
Dynamic: license-file
